{
"name":"dagger",
"fetch_time":0.276,
"eval_time":0.198,
"source":{
"url":"https://github.com/dagger/nix",
"rev":"1b634d4d8d78e50c6cbf8899238c946964b10249",
"sha256":"08448w4ggjsvqvv14zc68zxv4dz1a3c6qp446pg1qx0swmgjbh5r",
"date":null
},
"source_storepath":"/nix/store/fnd39d09jiivb6zmkhj134xj6vvimb05-source",
"nixpkgs_storepath":"/nix/store/v466hqszpfnwv2g57gz5ljf3bq39q8kf-source",
"nur_combined_rev":"40c2491b37455010f92fb9add0a756f1441c5f9e",
"packages":{
"dagger":{
"meta":{
"available":true,
"broken":false,
"description":"Dagger is an integrated platform to orchestrate the delivery of applications",
"homepage":"https://dagger.io",
"insecure":false,
"license":{
"deprecated":false,
"free":true,
"fullName":"Apache License 2.0",
"redistributable":true,
"shortName":"asl20",
"spdxId":"Apache-2.0",
"url":"https://spdx.org/licenses/Apache-2.0.html"
},
"name":"dagger-0.11.2",
"outputsToInstall":[
"out"
],
"platforms":[
"aarch64-darwin",
"aarch64-linux",
"armv7l-linux",
"x86_64-darwin",
"x86_64-linux"
],
"position":"./pkgs/dagger/default.nix:53",
"sourceProvenance":[
{
"isSource":false,
"shortName":"binaryNativeCode"
}
],
"unfree":false,
"unsupported":false
},
"name":"dagger-0.11.2",
"outputName":"out",
"outputs":{
"out":null
},
"pname":"dagger",
"system":"x86_64-linux",
"version":"0.11.2"
}
}
}