{
"name":"friendsofshopware",
"fetch_time":0.438,
"eval_time":0.202,
"source":{
"url":"https://github.com/FriendsOfShopware/nur-packages/",
"rev":"63915b26c71efd967b08d38cc0616cea8628d095",
"sha256":"1vmv90p85lb0w2zilq38dlg182grlszpswp89agnkm2fv0g7j3xb",
"date":null
},
"source_storepath":"/nix/store/b47dxg8s06qhd8jk32d4n6l08xbndmbm-source",
"nixpkgs_storepath":"/nix/store/arybzdvx1yqn874mx63swpbldyqmn94p-source",
"nur_combined_rev":"f140c8b5f0c8cccb24d97125e7d32c3ed62c7445",
"packages":{
"shopware-cli":{
"meta":{
"available":true,
"broken":false,
"description":"Command line tool for Shopware 6",
"homepage":"https://sw-cli.fos.gg",
"insecure":false,
"license":{
"deprecated":false,
"free":true,
"fullName":"MIT License",
"redistributable":true,
"shortName":"mit",
"spdxId":"MIT",
"url":"https://spdx.org/licenses/MIT.html"
},
"name":"shopware-cli-0.5.4",
"outputsToInstall":[
"out"
],
"platforms":[
"aarch64-darwin",
"aarch64-linux",
"x86_64-darwin",
"x86_64-linux"
],
"position":"./pkgs/shopware-cli/default.nix:51",
"sourceProvenance":[
{
"isSource":false,
"shortName":"binaryNativeCode"
}
],
"unfree":false,
"unsupported":false
},
"name":"shopware-cli-0.5.4",
"outputName":"out",
"outputs":{
"out":null
},
"pname":"shopware-cli",
"system":"x86_64-linux",
"version":"0.5.4"
}
}
}