{
"name":"friendsofshopware",
"fetch_time":0.253,
"eval_time":0.196,
"source":{
"url":"https://github.com/FriendsOfShopware/nur-packages/",
"rev":"a0ef7cace508e703222dbf30b295c79cf406d6f1",
"sha256":"1qh687vyv80m3lixb4hc5zpbkc7jwk6b01scbj75awr0zas79hv8",
"date":null
},
"source_storepath":"/nix/store/q2k501xh5kyl3yxdhyp95jgrm25p86p6-source",
"nixpkgs_storepath":"/nix/store/gdvk4xv8rhsac0hxy2vmmgfl3ylcgxr4-source",
"nur_combined_rev":"dcf2a8a76ea8d9c1f06ccd11521b102bf7ac9ec0",
"packages":{
"shopware-cli":{
"meta":{
"available":true,
"broken":false,
"description":"Command line tool for Shopware 6",
"homepage":"https://sw-cli.fos.gg",
"insecure":false,
"license":{
"deprecated":false,
"free":true,
"fullName":"MIT License",
"redistributable":true,
"shortName":"mit",
"spdxId":"MIT",
"url":"https://spdx.org/licenses/MIT.html"
},
"name":"shopware-cli-0.4.62",
"outputsToInstall":[
"out"
],
"platforms":[
"aarch64-darwin",
"aarch64-linux",
"x86_64-darwin",
"x86_64-linux"
],
"position":"./pkgs/shopware-cli/default.nix:51",
"sourceProvenance":[
{
"isSource":false,
"shortName":"binaryNativeCode"
}
],
"unfree":false,
"unsupported":false
},
"name":"shopware-cli-0.4.62",
"outputName":"out",
"outputs":{
"out":null
},
"pname":"shopware-cli",
"system":"x86_64-linux",
"version":"0.4.62"
}
}
}