{
"name":"goreleaser",
"fetch_time":0.222,
"eval_time":0.209,
"source":{
"url":"https://github.com/goreleaser/nur",
"rev":"af0ccf2b6c1d6c3914486a99144a1d79698ebfc3",
"sha256":"09kxjr9gabalj1y0lxqlsqpadnfslbxs58plcz33pp47i20dxx25",
"date":null
},
"source_storepath":"/nix/store/lbwn0lv7852vdlxz3w1ycx3smrd2pfyp-source",
"nixpkgs_storepath":"/nix/store/854kywmsh85z6zhfvnw6adjpp8yjnw5s-source",
"nur_combined_rev":"285d888229656e60816e1cbfede3fbc299de4cb8",
"packages":{
"goreleaser":{
"meta":{
"available":true,
"broken":false,
"description":"Release engineering, simplified",
"homepage":"https://goreleaser.com",
"insecure":false,
"license":{
"deprecated":false,
"free":true,
"fullName":"MIT License",
"redistributable":true,
"shortName":"mit",
"spdxId":"MIT",
"url":"https://spdx.org/licenses/MIT.html"
},
"name":"goreleaser-2.7.0",
"outputsToInstall":[
"out"
],
"platforms":[
"aarch64-darwin",
"aarch64-linux",
"armv7l-linux",
"i686-linux",
"x86_64-darwin",
"x86_64-linux"
],
"position":"./pkgs/goreleaser/default.nix:51",
"sourceProvenance":[
{
"isSource":false,
"shortName":"binaryNativeCode"
}
],
"unfree":false,
"unsupported":false
},
"name":"goreleaser-2.7.0",
"outputName":"out",
"outputs":{
"out":null
},
"pname":"goreleaser",
"system":"x86_64-linux",
"version":"2.7.0"
},
"goreleaser-pro":{
"meta":{
"available":false,
"broken":false,
"description":"Release engineering, simplified.",
"homepage":"https://goreleaser.com",
"insecure":false,
"license":{
"deprecated":false,
"free":false,
"fullName":"Unfree",
"redistributable":false,
"shortName":"unfree"
},
"name":"goreleaser-pro-2.7.0",
"outputsToInstall":[
"out"
],
"platforms":[
"aarch64-darwin",
"aarch64-linux",
"armv6l-linux",
"i686-linux",
"x86_64-darwin",
"x86_64-linux"
],
"position":"./pkgs/goreleaser-pro/default.nix:51",
"sourceProvenance":[
{
"isSource":false,
"shortName":"binaryNativeCode"
}
],
"unfree":true,
"unsupported":false
},
"name":"goreleaser-pro-2.7.0",
"outputName":"out",
"outputs":{
"out":null
},
"pname":"goreleaser-pro",
"system":"x86_64-linux",
"version":"2.7.0"
}
}
}