{
"name":"lmdevv",
"fetch_time":0.802,
"eval_time":0.195,
"source":{
"url":"https://github.com/lmdevv/nur-packages",
"rev":"85e2f779c758b94a1000c0d88ee49ddb5259d3cc",
"sha256":"1fiyqhjh4svw4pp620rs53j92xqyz1w3kgc87d8ss4jws505fykz",
"date":null
},
"source_storepath":"/nix/store/ihrlqxw9rhc6fm1ypvshlzf76k57427a-source",
"nixpkgs_storepath":"/nix/store/sq7n9j80chmzda57d671szcysg6fdjfr-source",
"nur_combined_rev":"058aebae8cb80d4852eb210b2b6e8449d6b0ed85",
"packages":{
"cursor-agent":{
"meta":{
"available":false,
"broken":false,
"description":"Cursor AI Agent CLI",
"homepage":"https://cursor.com",
"insecure":false,
"license":{
"deprecated":false,
"free":false,
"fullName":"Unfree",
"redistributable":false,
"shortName":"unfree"
},
"longDescription":"The Cursor Agent CLI is a command-line interface from Cursor.\nIt provides a simple way to interact with AI Agents from the command line.\n",
"mainProgram":"cursor-agent",
"maintainers":[
"lmdevv"
],
"maintainersPosition":{
"column":5,
"file":"/nix/store/ihrlqxw9rhc6fm1ypvshlzf76k57427a-source/pkgs/cursor-agent/default.nix",
"line":91
},
"name":"cursor-agent-2025.08.25-896bbe1",
"outputsToInstall":[
"out"
],
"platforms":[
"x86_64-linux",
"aarch64-linux",
"x86_64-darwin",
"aarch64-darwin"
],
"position":"./pkgs/cursor-agent/default.nix:77",
"sourceProvenance":[
{
"isSource":false,
"shortName":"binaryNativeCode"
}
],
"unfree":true,
"unsupported":false
},
"name":"cursor-agent-2025.08.25-896bbe1",
"outputName":"out",
"outputs":{
"out":null
},
"pname":"cursor-agent",
"system":"x86_64-linux",
"version":"2025.08.25-896bbe1"
}
}
}