{
"name":"mrcpkgs",
"fetch_time":0.762,
"eval_time":0.199,
"source":{
"url":"https://github.com/mrcjkb/nur-packages",
"rev":"06d62aa8aed9892c0d2639005f687eb3c81ba1fe",
"sha256":"1jl5bi7b1czigasabwhpbx6h02km512hp3dfmlccbiifnz9d2yr8",
"date":null
},
"source_storepath":"/nix/store/cavbw2bw993zdqiy34q5j669q7f3b33w-source",
"nixpkgs_storepath":"/nix/store/nynmib7zc00icj5p57agnjm8r6arjm0l-source",
"nur_combined_rev":"19782342367136d4f631e71ae2cb40f088abce2f",
"packages":{
"manix-fzf":{
"meta":{
"available":true,
"broken":false,
"insecure":false,
"mainProgram":"manix-fzf",
"maintainers":[],
"name":"manix-fzf",
"outputsToInstall":[
"out"
],
"position":"<nixpkgs> + /pkgs/build-support/trivial-builders/default.nix:80",
"unfree":false,
"unsupported":false
},
"name":"manix-fzf",
"outputName":"out",
"outputs":{
"out":null
},
"pname":"manix-fzf",
"system":"x86_64-linux",
"version":""
},
"nextcloud-no-de":{
"meta":{
"available":true,
"broken":false,
"insecure":false,
"maintainers":[],
"name":"nextcloud-nd",
"outputsToInstall":[
"out"
],
"position":"<nixpkgs> + /pkgs/build-support/trivial-builders/default.nix:617",
"unfree":false,
"unsupported":false
},
"name":"nextcloud-nd",
"outputName":"out",
"outputs":{
"out":null
},
"pname":"nextcloud-nd",
"system":"x86_64-linux",
"version":""
},
"yubikee-smartvpn":{
"meta":{
"available":true,
"broken":false,
"insecure":false,
"maintainers":[],
"name":"yubikee-smartvpn",
"outputsToInstall":[
"out"
],
"position":"<nixpkgs> + /pkgs/build-support/trivial-builders/default.nix:617",
"unfree":false,
"unsupported":false
},
"name":"yubikee-smartvpn",
"outputName":"out",
"outputs":{
"out":null
},
"pname":"yubikee-smartvpn",
"system":"x86_64-linux",
"version":""
}
}
}