{
"name":"nltch",
"fetch_time":0.731,
"eval_time":0.237,
"source":{
"url":"https://github.com/nl-tch/nur-packages",
"rev":"e437b0c49b6ffc8475257efb1399ca75a0b34ae2",
"sha256":"1my222z1gc9mjik0cmr36p2z087pdbv78sjz00spriq82ww0vcaf",
"date":null
},
"source_storepath":"/nix/store/b177l38sasqfc4jfzn2acjpc8jc2apqk-source",
"nixpkgs_storepath":"/nix/store/gxwv36g59813dh5f46qjnwsps5r7n51z-source",
"nur_combined_rev":"18a7ca776c2c7030a6a704824067c59985b90aa8",
"packages":{
"ciscoPacketTracer8":{
"meta":{
"available":false,
"broken":false,
"description":"Network simulation tool from Cisco",
"homepage":"https://www.netacad.com/courses/packet-tracer",
"identifiers":{
"cpeParts":{
"edition":"*",
"language":"*",
"other":"*",
"part":"a",
"product":"ciscoPacketTracer8",
"sw_edition":"*",
"target_hw":"*",
"target_sw":"*"
},
"possibleCPEs":[],
"v1":{
"cpeParts":{
"edition":"*",
"language":"*",
"other":"*",
"part":"a",
"product":"ciscoPacketTracer8",
"sw_edition":"*",
"target_hw":"*",
"target_sw":"*"
},
"possibleCPEs":[]
}
},
"insecure":false,
"license":{
"deprecated":false,
"free":false,
"fullName":"Unfree",
"redistributable":false,
"shortName":"unfree"
},
"mainProgram":"packettracer8",
"maintainers":[
{
"email":"gutyina.gergo.2@gmail.com",
"github":"gepbird",
"githubId":29818440,
"keys":[
{
"fingerprint":"RoAfvqa6w1l8Vdm3W60TDXurYwJ6h03VEGD+wDNGEwc"
},
{
"fingerprint":"MP2UpIRtJpbFFqyucP431H/FPCfn58UhEUTro4lXtRs"
}
],
"name":"Gutyina Gerg\u0151"
}
],
"maintainersPosition":{
"column":5,
"file":"/nix/store/gxwv36g59813dh5f46qjnwsps5r7n51z-source/pkgs/by-name/ci/ciscoPacketTracer8/package.nix",
"line":172
},
"name":"ciscoPacketTracer8-8.2.2",
"outputsToInstall":[
"out"
],
"platforms":[
"x86_64-linux"
],
"position":"<nixpkgs> + /pkgs/by-name/ci/ciscoPacketTracer8/package.nix:168",
"sourceProvenance":[
{
"isSource":false,
"shortName":"binaryNativeCode"
}
],
"unfree":true,
"unsupported":false
},
"name":"ciscoPacketTracer8-8.2.2",
"outputName":"out",
"outputs":{
"out":null
},
"pname":"ciscoPacketTracer8",
"system":"x86_64-linux",
"version":"8.2.2"
},
"spotify-adblock":{
"meta":{
"available":false,
"broken":false,
"description":"Play music from the Spotify music service",
"homepage":"https://www.spotify.com/",
"identifiers":{
"cpeParts":{
"edition":"*",
"language":"*",
"other":"*",
"part":"a",
"product":"spotify",
"sw_edition":"*",
"target_hw":"*",
"target_sw":"*"
},
"possibleCPEs":[],
"v1":{
"cpeParts":{
"edition":"*",
"language":"*",
"other":"*",
"part":"a",
"product":"spotify",
"sw_edition":"*",
"target_hw":"*",
"target_sw":"*"
},
"possibleCPEs":[]
}
},
"insecure":false,
"license":{
"deprecated":false,
"free":false,
"fullName":"Unfree",
"redistributable":false,
"shortName":"unfree"
},
"mainProgram":"spotify",
"maintainers":[
{
"email":"ftrvxmtrx@gmail.com",
"github":"ftrvxmtrx",
"githubId":248148,
"name":"Sigrid Solveig Hafl\u00ednud\u00f3ttir"
},
{
"email":"sheena.artrip@gmail.com",
"github":"sheenobu",
"githubId":1443459,
"name":"Sheena Artrip"
},
{
"email":"timokau@zoho.com",
"github":"timokau",
"githubId":3799330,
"name":"Timo Kaufmann"
},
{
"email":"maximilian@mbosch.me",
"github":"Ma27",
"githubId":6025220,
"matrix":"@ma27:nicht-so.sexy",
"name":"Maximilian Bosch"
}
],
"maintainersPosition":{
"column":5,
"file":"/nix/store/gxwv36g59813dh5f46qjnwsps5r7n51z-source/pkgs/by-name/sp/spotify/linux.nix",
"line":233
},
"name":"spotify-1.2.63.394.g126b0d89",
"outputsToInstall":[
"out"
],
"platforms":[
"x86_64-linux",
"x86_64-darwin",
"aarch64-darwin"
],
"position":"<nixpkgs> + /pkgs/by-name/sp/spotify/package.nix:17",
"sourceProvenance":[
{
"isSource":false,
"shortName":"binaryNativeCode"
}
],
"unfree":true,
"unsupported":false
},
"name":"spotify-1.2.63.394.g126b0d89",
"outputName":"out",
"outputs":{
"out":null
},
"pname":"spotify",
"system":"x86_64-linux",
"version":"1.2.63.394.g126b0d89"
}
}
}