{"name":"nousefreak","fetch_time":3.436,"eval_time":4.515,"source":{"url":"https://github.com/NoUseFreak/nix-packages","rev":"a7efa86b438a5b8824bcac7890bd641e99ff337f","sha256":"1d9qpf3daq4whh8k8a5blidbhhway6dcn6xnr7gdpi8djal9sd7y","date":null},"source_storepath":"/nix/store/yx131fvzh9bzfj6krqbxhag6w7vn4pdj-source","nur_combined_rev":"3349ca1ba2148eb0b40d9e5fafcca0b1e1e09ddf","packages":{"projecthelper":{"meta":{"available":true,"broken":false,"description":"Project helper tries to save time","homepage":"https://github.com/nousefreak/projecthelper","insecure":false,"license":{"deprecated":false,"free":true,"fullName":"MIT License","redistributable":true,"shortName":"mit","spdxId":"MIT","url":"https://spdx.org/licenses/MIT.html"},"name":"projecthelper-0.6.0","outputsToInstall":["out"],"platforms":["aarch64-darwin","aarch64-linux","i686-linux","x86_64-darwin","x86_64-linux"],"position":"pkgs/projecthelper/default.nix:48","sourceProvenance":[{"isSource":false,"shortName":"binaryNativeCode"}],"unfree":false,"unsupported":false},"name":"projecthelper-0.6.0","outputName":"out","outputs":{"out":null},"pname":"projecthelper","system":"x86_64-linux","version":"0.6.0"}}}